pyesi_openapi/__init__.py
pyesi_openapi/api_client.py
pyesi_openapi/api_response.py
pyesi_openapi/configuration.py
pyesi_openapi/exceptions.py
pyesi_openapi/py.typed
pyesi_openapi/rest.py
pyesi_openapi/api/__init__.py
pyesi_openapi/api/alliance_api.py
pyesi_openapi/api/assets_api.py
pyesi_openapi/api/calendar_api.py
pyesi_openapi/api/character_api.py
pyesi_openapi/api/clones_api.py
pyesi_openapi/api/contacts_api.py
pyesi_openapi/api/contracts_api.py
pyesi_openapi/api/corporation_api.py
pyesi_openapi/api/dogma_api.py
pyesi_openapi/api/faction_warfare_api.py
pyesi_openapi/api/fittings_api.py
pyesi_openapi/api/fleets_api.py
pyesi_openapi/api/incursions_api.py
pyesi_openapi/api/industry_api.py
pyesi_openapi/api/insurance_api.py
pyesi_openapi/api/killmails_api.py
pyesi_openapi/api/location_api.py
pyesi_openapi/api/loyalty_api.py
pyesi_openapi/api/mail_api.py
pyesi_openapi/api/market_api.py
pyesi_openapi/api/meta_api.py
pyesi_openapi/api/planetary_interaction_api.py
pyesi_openapi/api/routes_api.py
pyesi_openapi/api/search_api.py
pyesi_openapi/api/skills_api.py
pyesi_openapi/api/sovereignty_api.py
pyesi_openapi/api/status_api.py
pyesi_openapi/api/universe_api.py
pyesi_openapi/api/user_interface_api.py
pyesi_openapi/api/wallet_api.py
pyesi_openapi/api/wars_api.py
pyesi_openapi/models/__init__.py
pyesi_openapi/models/alliances_alliance_id_contacts_get_inner.py
pyesi_openapi/models/alliances_alliance_id_contacts_labels_get_inner.py
pyesi_openapi/models/alliances_alliance_id_get.py
pyesi_openapi/models/alliances_alliance_id_icons_get.py
pyesi_openapi/models/characters_affiliation_post_inner.py
pyesi_openapi/models/characters_character_id_agents_research_get_inner.py
pyesi_openapi/models/characters_character_id_assets_get_inner.py
pyesi_openapi/models/characters_character_id_assets_locations_post_inner.py
pyesi_openapi/models/characters_character_id_assets_locations_post_inner_position.py
pyesi_openapi/models/characters_character_id_assets_names_post_inner.py
pyesi_openapi-0.1.2.dist-info/licenses/LICENSE
pyesi_openapi-0.1.2.dist-info/METADATA
pyesi_openapi-0.1.2.dist-info/WHEEL
pyesi_openapi-0.1.2.dist-info/top_level.txt
pyesi_openapi-0.1.2.dist-info/RECORD
