Metadata-Version: 2.4
Name: pyesi_openapi
Version: 0.1.2
Summary: PyESI (OpenAPI) - EVE Stable Infrastructure (ESI)
Home-page: https://github.com/arxbombus/pyesi-openapi
Author: arxbombus
Author-email: arxbombus <arxbombus@gmail.com>
License-Expression: MIT
Project-URL: Repository, https://github.com/arxbombus/pyesi-openapi
Keywords: OpenAPI,OpenAPI-Generator,PyESI (OpenAPI) - EVE Stable Infrastructure (ESI)
Requires-Python: >=3.9
License-File: LICENSE
Requires-Dist: urllib3<3.0.0,>=2.1.0
Requires-Dist: python-dateutil>=2.8.2
Requires-Dist: pydantic>=2
Requires-Dist: typing-extensions>=4.7.1
Requires-Dist: lazy-imports<2,>=1
Dynamic: author
Dynamic: home-page
Dynamic: license-file
